Project/__init__.py
Project/outliers.py
vivek_101703624-0.0.3.dist-info/LICENSE.txt
vivek_101703624-0.0.3.dist-info/METADATA
vivek_101703624-0.0.3.dist-info/WHEEL
vivek_101703624-0.0.3.dist-info/entry_points.txt
vivek_101703624-0.0.3.dist-info/top_level.txt
vivek_101703624-0.0.3.dist-info/RECORD
