Metadata-Version: 2.1
Name: vivek-101703624
Version: 0.0.3
Summary: Outliers
Home-page: 
Author: Vivek Khanduja
Author-email: vkhanduja28@gmail.com
License: UNKNOWN
Platform: UNKNOWN
Classifier: Programming Language :: Python :: 3
Classifier: License :: OSI Approved :: MIT License
Classifier: Operating System :: OS Independent
Requires-Python: >=3.6
Requires-Dist: requests
